Metadata-Version: 2.1
Name: GeoSolver
Version: 1.0.2
Summary: A library to solve 3D-geometry
Home-page: https://github.com/KareEnges/GeoSolver
Author: EngelsVon/FengHaoen
Author-email: engelsvon3@gmail.com
License: MIT
Classifier: Programming Language :: Python :: 3
Classifier: License :: OSI Approved :: MIT License
Classifier: Operating System :: OS Independent
